todo/__init__.py
todo/placeholder.py
todo_placeholder-2.0.1.dist-info/LICENSE
todo_placeholder-2.0.1.dist-info/METADATA
todo_placeholder-2.0.1.dist-info/WHEEL
todo_placeholder-2.0.1.dist-info/top_level.txt
todo_placeholder-2.0.1.dist-info/RECORD
