Metadata-Version: 2.1
Name: todo-placeholder
Version: 2.0.1
Summary: Use a terminal session to lazily write python source code
Home-page: https://github.com/antonpaquin/todo-placeholder
Author: Anton Paquin
Author-email: python@antonpaqu.in
License: UNKNOWN
Platform: UNKNOWN
